pyforfluids/__init__.py
pyforfluids/core.py
pyforfluids/fortran/__init__.py
pyforfluids/fortran/gerg2008f.cp38-win_amd64.pyd
pyforfluids/fortran/thermo_props.cp38-win_amd64.pyd
pyforfluids/models/__init__.py
pyforfluids/models/gerg2008.py
pyforfluids-0.0.1a3.dist-info/LICENSE
pyforfluids-0.0.1a3.dist-info/METADATA
pyforfluids-0.0.1a3.dist-info/WHEEL
pyforfluids-0.0.1a3.dist-info/top_level.txt
pyforfluids-0.0.1a3.dist-info/RECORD
