Metadata-Version: 2.1
Name: pyforfluids
Version: 0.0.1a3
Summary: Fluid's thermodynamic properties
Home-page: https://github.com/fedebenelli/pyforfluids
Author: Federico E. Benelli; M. Candelaria Arpajou
Author-email: federico.benelli@mi.unc.edu.ar
License: MIT
Keywords: Thermodynamic,Fluids,Properties,EoS
Platform: UNKNOWN
Classifier: Development Status :: 2 - Pre-Alpha
Classifier: Intended Audience :: Education
Classifier: Intended Audience :: Science/Research
Classifier: License :: OSI Approved :: MIT License
Classifier: Operating System :: MacOS :: MacOS X
Classifier: Operating System :: POSIX :: Linux
Classifier: Programming Language :: Fortran
Classifier: Programming Language :: Python
Classifier: Programming Language :: Python :: 3.7
Classifier: Programming Language :: Python :: 3.8
Classifier: Programming Language :: Python :: 3.9
Classifier: Programming Language :: Python :: Implementation :: CPython
Classifier: Topic :: Scientific/Engineering
Requires-Dist: numpy (>=1.21.2)
Requires-Dist: pandas (>=1.3.5)
Requires-Dist: scipy (==1.7.3)
